caireCovid/__init__.py
caireCovid/qa_utils.py
caireCovid/biobert/__init__.py
caireCovid/biobert/modeling.py
caireCovid/biobert/predictor_biobert.py
caireCovid/biobert/tokenization.py
caireCovid/mrqa/__init__.py
caireCovid/mrqa/data_utils.py
caireCovid/mrqa/predictor_kaggle.py
caireCovid/mrqa/prepro_utils.py
caireCovid-0.1.8.dist-info/METADATA
caireCovid-0.1.8.dist-info/WHEEL
caireCovid-0.1.8.dist-info/top_level.txt
caireCovid-0.1.8.dist-info/RECORD
